dandy/__init__.py
dandy/conf.py
dandy/consts.py
dandy/default_settings.py
dandy/cache/__init__.py
dandy/cache/cache.py
dandy/cache/decorators.py
dandy/cache/exceptions.py
dandy/cache/tools.py
dandy/cache/memory/__init__.py
dandy/cache/memory/cache.py
dandy/cache/memory/decorators.py
dandy/cache/sqlite/__init__.py
dandy/cache/sqlite/cache.py
dandy/cache/sqlite/connection.py
dandy/cache/sqlite/decorators.py
dandy/calculator/__init__.py
dandy/calculator/llm_calculator.py
dandy/calculator/calculations/__init__.py
dandy/calculator/calculations/calculations.py
dandy/calculator/calculations/llm/__init__.py
dandy/calculator/calculations/llm/model_calculations.py
dandy/core/__init__.py
dandy/core/debug.py
dandy/core/exceptions.py
dandy/core/singleton.py
dandy/core/utils.py
dandy/core/config/__init__.py
dandy/core/config/config.py
dandy/core/connector/__init__.py
dandy/core/connector/exceptions.py
dandy/core/future/__init__.py
dandy/core/future/exceptions.py
dandy/core/future/future.py
dandy/core/future/tools.py
dandy/core/path/__init__.py
dandy/core/path/tools.py
dandy/core/service/__init__.py
dandy/core/service/exceptions.py
dandy/core/service/mixin.py
dandy/core/service/service.py
dandy/core/typing/__init__.py
dandy/core/typing/consts.py
dandy/core/typing/exceptions.py
dandy/core/typing/registry.py
dandy/core/typing/tools.py
dandy/core/typing/typed_kwargs.py
dandy/core/typing/typing.py
dandy/http/__init__.py
dandy/http/connector.py
dandy/http/exceptions.py
dandy/http/mixin.py
dandy/http/service.py
dandy/http/url.py
dandy/http/intelligence/__init__.py
dandy/http/intelligence/intel.py
dandy/intel/__init__.py
dandy/intel/exceptions.py
dandy/intel/factory.py
dandy/intel/generator.py
dandy/intel/intel.py
dandy/intel/mixin.py
dandy/intel/service.py
dandy/intel/typing.py
dandy/intel/field/__init__.py
dandy/intel/field/annotation.py
dandy/llm/__init__.py
dandy/llm/conf.py
dandy/llm/exceptions.py
dandy/llm/mixin.py
dandy/llm/recorder.py
dandy/llm/service.py
dandy/llm/utils.py
dandy-1.3.5.dist-info/licenses/LICENSE.md
dandy-1.3.5.dist-info/METADATA
dandy-1.3.5.dist-info/WHEEL
dandy-1.3.5.dist-info/entry_points.txt
dandy-1.3.5.dist-info/top_level.txt
dandy-1.3.5.dist-info/RECORD
